relay_controller/__init__.py
relay_controller/controller.py
relay_controller-1.1.1.dist-info/METADATA
relay_controller-1.1.1.dist-info/WHEEL
relay_controller-1.1.1.dist-info/top_level.txt
relay_controller-1.1.1.dist-info/RECORD
