Metadata-Version: 2.1
Name: relay-controller
Version: 1.1.1
Summary: A relay controller module for Python.
Home-page: https://github.com/mnedev-cell/relay_controller
Author: DEVMNE
Author-email: mne@yaposarl.ma
Classifier: Programming Language :: Python :: 3
Classifier: License :: OSI Approved :: MIT License
Classifier: Operating System :: OS Independent
Requires-Python: >=3.6
Requires-Dist: pyhid-usb-relay
